auto_uwsgi/__init__.py
auto_uwsgi/deployment.py
auto_uwsgi-1.0.1.dist-info/LICENSE
auto_uwsgi-1.0.1.dist-info/METADATA
auto_uwsgi-1.0.1.dist-info/WHEEL
auto_uwsgi-1.0.1.dist-info/top_level.txt
auto_uwsgi-1.0.1.dist-info/RECORD
