Metadata-Version: 2.1
Name: auto-uwsgi
Version: 1.0.1
Summary: Auto deploy django project on linux using nginx and uwsgi
Home-page: https://github.com/nghiemIUH/auto-uwsgi
Author: Van Nghiem
Author-email: vannghiem848@gmail.com
License: MIT
Platform: UNKNOWN
Classifier: Intended Audience :: Developers
Classifier: License :: OSI Approved :: MIT License
Classifier: Programming Language :: Python
Classifier: Programming Language :: Python :: 3
Classifier: Programming Language :: Python :: 3.6
Classifier: Programming Language :: Python :: 3.7
Classifier: Programming Language :: Python :: 3.8
Classifier: Programming Language :: Python :: 3.9
Classifier: Operating System :: OS Independent
License-File: LICENSE
Requires-Dist: uwsgi
